b3d/__init__.py
b3d/b3d_.py
b3d/cli.py
b3d/aws/__init__.py
b3d/aws/api_gateway.py
b3d/aws/ec2.py
b3d/aws/helpers.py
b3d/aws/iam.py
b3d/aws/kms.py
b3d/aws/lambda_.py
b3d/aws/resource_groups_tagging.py
b3d/aws/s3.py
b3d/aws/ssm.py
b3d/delete/__init__.py
b3d/delete/api_gateway.py
b3d/delete/ec2.py
b3d/delete/iam.py
b3d/delete/kms.py
b3d/delete/lambda_.py
b3d/delete/s3.py
b3d/delete/ssm.py
b3d/delete/unsupported.py
b3d/utils/__init__.py
b3d/utils/loading.py
b3d/utils/log_msg.py
b3d-0.1.7.dist-info/LICENSE
b3d-0.1.7.dist-info/METADATA
b3d-0.1.7.dist-info/WHEEL
b3d-0.1.7.dist-info/top_level.txt
b3d-0.1.7.dist-info/RECORD
