Metadata-Version: 2.1
Name: b3d
Version: 0.1.7
Summary: Boto3 utility library that supports deletion of collections of AWS resources (such as temporary resources created during unit tests).
Author: Ben Getchell
Author-email: bengetch@gmail.com
License: MIT License
Project-URL: homepage, https://github.com/nthparty/b3d
Project-URL: repository, https://github.com/nthparty/b3d
Requires-Python: >=3.7
License-File: LICENSE
Requires-Dist: b3q (~=0.4)
Requires-Dist: boto3 (~=1.24)
Requires-Dist: jmespath (~=1.0)
Requires-Dist: python-dateutil (~=2.8)
Requires-Dist: s3transfer (~=0.6)
Requires-Dist: six (~=1.16)
Requires-Dist: urllib3 (~=1.26)
Provides-Extra: lint
Requires-Dist: pylint (~=2.14.0) ; extra == 'lint'
Provides-Extra: publish
Requires-Dist: build (~=0.8) ; extra == 'publish'
Requires-Dist: twine (~=4.0) ; extra == 'publish'
Provides-Extra: test
Requires-Dist: pytest (~=7.0) ; extra == 'test'
Requires-Dist: terrorform (~=0.2) ; extra == 'test'
